qrizzclient/AuthEndpoints.py
qrizzclient/ChatEndpoints.py
qrizzclient/Client.py
qrizzclient/Config.py
qrizzclient/ConnectDbEndpoints.py
qrizzclient/Endpoints.py
qrizzclient/Exceptions.py
qrizzclient/FileEndpoints.py
qrizzclient/Session.py
qrizzclient/__init__.py
kskclient-0.1.1.dist-info/METADATA
kskclient-0.1.1.dist-info/WHEEL
kskclient-0.1.1.dist-info/top_level.txt
kskclient-0.1.1.dist-info/RECORD
