Metadata-Version: 2.1
Name: kskclient
Version: 0.1.1
Summary: A client library for interacting with the Qrizz API
Home-page: https://github.com/rmialgorizz/qrizz-dsc/tree/python-sdk-dev/qrizzclient
Author: Kiran
Author-email: kirankulkarni682@gmail.com
Classifier: Programming Language :: Python :: 3
Classifier: License :: OSI Approved :: MIT License
Classifier: Operating System :: OS Independent
Requires-Python: >=3.6
